quansyn/__init__.py
quansyn/depval.py
quansyn/lawfitter.py
quansyn/lingnet.py
quansyn-0.0.12.dist-info/LICENSE
quansyn-0.0.12.dist-info/METADATA
quansyn-0.0.12.dist-info/WHEEL
quansyn-0.0.12.dist-info/top_level.txt
quansyn-0.0.12.dist-info/RECORD
