Metadata-Version: 2.1
Name: quansyn
Version: 0.0.12
Summary: A package for quantitative syntax analysis
Home-page: https://github.com/YuhuYang/QuanSyn
Author: Mu Yang
Author-email: yangmufy@163.com
License: UNKNOWN
Platform: UNKNOWN
Classifier: Programming Language :: Python :: 3
Classifier: License :: OSI Approved :: MIT License
Classifier: Operating System :: OS Independent
Requires-Python: >=3.6
Requires-Dist: numpy (>=1.21.5)
Requires-Dist: pandas (>=1.4.4)
Requires-Dist: conllu (>=4.5.3)
Requires-Dist: scikit-learn (>=1.0.2)
Requires-Dist: scipy (>=1.9.1)
